scratch/transaction.py
scratch/extension.py
scratch/tests.py
scratch/communication.py
scratch/__init__.py
paywithscratch-0.3.0.dist-info/DESCRIPTION.rst
paywithscratch-0.3.0.dist-info/top_level.txt
paywithscratch-0.3.0.dist-info/METADATA
paywithscratch-0.3.0.dist-info/metadata.json
paywithscratch-0.3.0.dist-info/WHEEL
paywithscratch-0.3.0.dist-info/RECORD
