Metadata-Version: 2.0
Name: paywithscratch
Version: 0.3.0
Summary: Scratch Payment Library
Home-page: http://www.paywithscratch.com/
Author: Mu, LLC
Author-email: eric@paywithscratch.com
License: MIT
Keywords: scratch online payments
Platform: UNKNOWN
Classifier: Development Status :: 4 - Beta
Classifier: Environment :: Web Environment
Classifier: Intended Audience :: Financial and Insurance Industry
Classifier: License :: OSI Approved :: MIT License
Classifier: Programming Language :: Python :: 2
Classifier: Programming Language :: Python :: 2.7
Classifier: Topic :: Office/Business :: Financial :: Point-Of-Sale
Requires-Dist: oauthlib
Requires-Dist: pycrypto
Requires-Dist: python-openid
Requires-Dist: requests
Requires-Dist: requests-oauthlib
